kalibr/__init__.py
kalibr/__main__.py
kalibr/capsule_middleware.py
kalibr/client.py
kalibr/collector.py
kalibr/context.py
kalibr/cost_adapter.py
kalibr/decorators.py
kalibr/intelligence.py
kalibr/kalibr.py
kalibr/kalibr_app.py
kalibr/models.py
kalibr/redaction.py
kalibr/schemas.py
kalibr/simple_tracer.py
kalibr/tokens.py
kalibr/trace_capsule.py
kalibr/trace_models.py
kalibr/tracer.py
kalibr/types.py
kalibr/utils.py
kalibr/cli/__init__.py
kalibr/cli/capsule_cmd.py
kalibr/cli/deploy_cmd.py
kalibr/cli/main.py
kalibr/cli/run.py
kalibr/cli/serve.py
kalibr/instrumentation/__init__.py
kalibr/instrumentation/anthropic_instr.py
kalibr/instrumentation/base.py
kalibr/instrumentation/google_instr.py
kalibr/instrumentation/openai_instr.py
kalibr/instrumentation/registry.py
kalibr/middleware/__init__.py
kalibr/middleware/auto_tracer.py
kalibr_crewai/__init__.py
kalibr_crewai/callbacks.py
kalibr_crewai/instrumentor.py
kalibr_langchain/__init__.py
kalibr_langchain/async_callback.py
kalibr_langchain/callback.py
kalibr_openai_agents/__init__.py
kalibr_openai_agents/processor.py
kalibr-1.2.3.dist-info/LICENSE
kalibr-1.2.3.dist-info/METADATA
kalibr-1.2.3.dist-info/WHEEL
kalibr-1.2.3.dist-info/entry_points.txt
kalibr-1.2.3.dist-info/top_level.txt
kalibr-1.2.3.dist-info/RECORD
