Metadata-Version: 2.2
Name: kalibr
Version: 1.2.3
Summary: Unified LLM Observability & Multi-Model AI Integration Framework - Deploy to GPT, Claude, Gemini, Copilot with full telemetry.
Author-email: Kalibr Team <support@kalibr.systems>
License: Apache-2.0
Project-URL: Homepage, https://github.com/kalibr-ai/kalibr-sdk-python
Project-URL: Documentation, https://kalibr.systems/docs
Project-URL: Repository, https://github.com/kalibr-ai/kalibr-sdk-python
Project-URL: Issues, https://github.com/kalibr-ai/kalibr-sdk-python/issues
Keywords: ai,mcp,gpt,claude,gemini,copilot,openai,anthropic,google,microsoft,observability,telemetry,tracing,llm,schema-generation,api,multi-model,langchain,crewai
Classifier: Development Status :: 4 - Beta
Classifier: Intended Audience :: Developers
Classifier: License :: OSI Approved :: Apache Software License
Classifier: Programming Language :: Python :: 3
Classifier: Programming Language :: Python :: 3.8
Classifier: Programming Language :: Python :: 3.9
Classifier: Programming Language :: Python :: 3.10
Classifier: Programming Language :: Python :: 3.11
Classifier: Programming Language :: Python :: 3.12
Classifier: Topic :: Software Development :: Libraries :: Python Modules
Classifier: Topic :: Scientific/Engineering :: Artificial Intelligence
Requires-Python: >=3.9
License-File: LICENSE
Requires-Dist: httpx>=0.27.0
Requires-Dist: tiktoken>=0.8.0
Requires-Dist: fastapi>=0.110.1
Requires-Dist: uvicorn>=0.25.0
Requires-Dist: pydantic>=2.6.4
Requires-Dist: typer>=0.9.0
Requires-Dist: python-multipart>=0.0.9
Requires-Dist: rich>=10.0.0
Requires-Dist: requests>=2.31.0
Requires-Dist: opentelemetry-api>=1.20.0
Requires-Dist: opentelemetry-sdk>=1.20.0
Requires-Dist: opentelemetry-exporter-otlp>=1.20.0
Provides-Extra: langchain
Requires-Dist: langchain-core>=0.1.0; extra == "langchain"
Provides-Extra: langchain-openai
Requires-Dist: langchain-core>=0.1.0; extra == "langchain-openai"
Requires-Dist: langchain-openai>=0.1.0; extra == "langchain-openai"
Provides-Extra: langchain-anthropic
Requires-Dist: langchain-core>=0.1.0; extra == "langchain-anthropic"
Requires-Dist: langchain-anthropic>=0.1.0; extra == "langchain-anthropic"
Provides-Extra: langchain-google
Requires-Dist: langchain-core>=0.1.0; extra == "langchain-google"
Requires-Dist: langchain-google-genai>=0.0.10; extra == "langchain-google"
Provides-Extra: langchain-all
Requires-Dist: langchain-core>=0.1.0; extra == "langchain-all"
Requires-Dist: langchain-openai>=0.1.0; extra == "langchain-all"
Requires-Dist: langchain-anthropic>=0.1.0; extra == "langchain-all"
Requires-Dist: langchain-google-genai>=0.0.10; extra == "langchain-all"
Provides-Extra: crewai
Requires-Dist: crewai>=0.28.0; extra == "crewai"
Provides-Extra: openai-agents
Requires-Dist: openai-agents>=0.0.3; extra == "openai-agents"
Provides-Extra: integrations
Requires-Dist: langchain-core>=0.1.0; extra == "integrations"
Requires-Dist: crewai>=0.28.0; extra == "integrations"
Requires-Dist: openai-agents>=0.0.3; extra == "integrations"
Provides-Extra: dev
Requires-Dist: pytest>=7.4.0; extra == "dev"
Requires-Dist: pytest-asyncio>=0.21.0; extra == "dev"
Requires-Dist: black>=23.0.0; extra == "dev"
Requires-Dist: ruff>=0.1.0; extra == "dev"
